peepo.py
peepo-0.1.0.dist-info/METADATA
peepo-0.1.0.dist-info/WHEEL
peepo-0.1.0.dist-info/top_level.txt
peepo-0.1.0.dist-info/RECORD
