Metadata-Version: 2.1
Name: peepo
Version: 0.1.0
Summary: PEE PO PEE PO
Home-page: https://github.com/luclepot/peepo
Author: peepo
Author-email: peepo@gmail.edu
License: UNKNOWN
Platform: UNKNOWN
Classifier: Programming Language :: Python :: 3
Classifier: License :: OSI Approved :: MIT License
Classifier: Operating System :: OS Independent
Requires-Python: >=3.6
Requires-Dist: pyo
Requires-Dist: numpy
Requires-Dist: pandas (>=0.25.1)
